CHANGES.rst
LICENSE
MANIFEST.in
README.rst
setup.py
sengiri/__init__.py
sengiri/sengiri.py
sengiri.egg-info/PKG-INFO
sengiri.egg-info/SOURCES.txt
sengiri.egg-info/dependency_links.txt
sengiri.egg-info/top_level.txt