Metadata-Version: 1.1
Name: sengiri
Version: 0.2
Summary: Yet another sentence-level tokenizer for the Japanese text
Home-page: https://github.com/ikegami-yukino/sengiri
Author: Yukino Ikegami
Author-email: yknikgm@gmail.com
License: MIT License
Keywords: japanese,tokenizer,sentence,sentence-tokenizer
Platform: POSIX
Platform: Windows
Platform: Unix
Platform: MacOS
Classifier: Development Status :: 3 - Alpha
Classifier: Intended Audience :: Developers
Classifier: Intended Audience :: Information Technology
Classifier: License :: OSI Approved :: MIT License
Classifier: Natural Language :: Japanese
Classifier: Operating System :: MacOS
Classifier: Operating System :: Microsoft
Classifier: Operating System :: POSIX
Classifier: Programming Language :: Python :: 3.4
Classifier: Programming Language :: Python :: 3.5
Classifier: Programming Language :: Python :: 3.6
Classifier: Programming Language :: Python :: 3.7
Classifier: Topic :: Text Processing
